tingcli/__init__.py
tingcli/utils.py
tingcli-0.5.data/scripts/tingcli
tingcli-0.5.dist-info/METADATA
tingcli-0.5.dist-info/WHEEL
tingcli-0.5.dist-info/top_level.txt
tingcli-0.5.dist-info/RECORD
