Metadata-Version: 2.1
Name: tingcli
Version: 0.5
Summary: ting项目相关命令行工具
Home-page: UNKNOWN
Author: ocean.wang
Author-email: tomcat1991@126.com
License: MIT
Platform: UNKNOWN
Classifier: Programming Language :: Python :: 3
Classifier: License :: OSI Approved :: MIT License
Classifier: Operating System :: OS Independent
Requires-Dist: coloredlogs
Requires-Dist: fire
Requires-Dist: qrcode
